{
  "errInfo": "None",
  "rescode": "200",
  "movie": {
    "movieId":"1",
    "name":"功夫熊猫3",
    "url":"http://localhost/clear-hotel-mobile/src/api/demo.mp4",
    "imgUrl":"http://localhost/clear-hotel-mobile/src/api/poster.jpg",
    "intro1":"上映时间：2015/11/16",
    "intro2":"成龙、周杰伦惊喜献声",
    "intro":"介绍详情页面的文字介绍介绍详情页面的文字介绍介绍详情页面的文字介绍介绍详情页面的文字介绍介绍详情页面的文字介绍介绍详情页面的文字介绍介绍详情页面的文字介绍介绍详情页面的文字介绍介绍详情页面的文字介绍介绍详情页面的文字介绍介绍详情页面的文字介绍介绍详情页面的文字介绍介绍详情页面的文字介绍介绍详情页面的文字介绍介绍详情页面的文字介绍介绍详情页面的文字介绍介绍详情页面的文字介绍介绍详情页面的文字介绍介绍详情页面的文字介绍介绍详情页面的文字介绍介绍详情页面的文字介绍介绍详情页面的文字介绍介绍详情页面的文字介绍介绍详情页面的文字介绍介绍详情页面的文字介绍介绍详情页面的文字介绍介绍详情页面的文字介绍介绍详情页面的文字介绍介绍详情页面的文字介绍介绍详情页面的文字介绍介绍详情页面的文字介绍介绍详情页面的文字介绍介绍详情页面的文字介绍介绍详情页面的文字介绍介绍详情页面的文字介绍介绍详情页面的文字介绍介绍详情页面的文字介绍介绍详情页面的文字介绍介绍详情页面的文字介绍介绍详情页面的文字介绍介绍详情页面的文字介绍介绍详情页面的文字介绍介绍详情页面的文字介绍介绍详情页面的文字介绍介绍详情页面的文字介绍介绍详情页面的文字介绍介绍详情页面的文字介绍介绍详情页面的文字介绍介绍详情页面的文字介绍介绍详情页面的文字介绍介绍详情页面的文字介绍介绍详情页面的文字介绍介绍详情页面的文字介绍"
  }
}